{
    "Group":
    [
      {
        "name": "Person1",
        "id": 11
      },
      {
        "name": "Person2",
        "id": 12
      },
      {
        "name": "Person3",
        "id": 13
      },
      {
        "name": "Person4",
        "id": 14
      },
      {
        "name": "Person5",
        "id": 15
      },
      {
        "name": "Person6",
        "id": 16
      },
      {
        "name": "Person7",
        "id": 17
      },
      {
        "name": "Person8",
        "id": 18
      },
      {
        "name": "Person9",
        "id": 19
      },
      {
        "name": "Person10",
        "id": 20
      }
    ]
}